Workbook

Sheet Datos
A1: País | B1: IVA | C1: Otros Impuestos | D1: Link | F1: Pais | G1: Cuotas | I1: Comisión | K1: Tipo Publicación | M1: IVA Argentina
A2: Argentina | B2: 0.21 | C2: 0.047 | D2: https://www.mercadolibre.com.ar/simulador-de-costos? | F2: Argentina | G2: Cuotas Int. Bajo | H2: =F2&G2 -> ArgentinaCuotas Int. Bajo | I2: 0.04 | K2: Clásica | M2: 0.21
A3: Uruguay | B3: 0.22 | C3: 0.01 | D3: https://www.mercadolibre.com.uy/simulador-de-costos? | F3: Argentina | G3: 3 Cuotas | H3: =F3&G3 -> Argentina3 Cuotas | I3: 0.084 | K3: 3 Cuotas | M3: 0.105
A4: Ecuador | B4: 0.15 | C4: 0.02 | D4: https://www.mercadolibre.com.ec/simulador-de-costos? | F4: Argentina | G4: 3 Cuotas Simples | H4: =F4&G4 -> Argentina3 Cuotas Simples | I4: 0.0655 | K4: 3 Cuotas Simples
A5: Colombia | B5: 0.19 | C5: 0.03 | D5: https://www.mercadolibre.com.co/simulador-de-costos? | F5: Argentina | G5: 6 Cuotas | H5: =F5&G5 -> Argentina6 Cuotas | I5: 0.123 | K5: 6 Cuotas
A6: Argentina | B6: 0.105 | C6: 0.041 | F6: Argentina | G6: 6 Cuotas Simples | H6: =F6&G6 -> Argentina6 Cuotas Simples | I6: 0.1248 | K6: 6 Cuotas Simples
A7: Pais | B7: Vertical | D7: Comisión | F7: Argentina | G7: 9 Cuotas | H7: =F7&G7 -> Argentina9 Cuotas | I7: 0.157 | K7: 9 Cuotas
A8: Argentina | B8: Zapatillas | C8: =A8&B8 -> ArgentinaZapatillas | D8: 0.14 | F8: Argentina | G8: 12 Cuotas | H8: =F8&G8 -> Argentina12 Cuotas | I8: 0.192 | K8: 12 Cuotas
A9: Argentina | B9: Repuestos | C9: =A9&B9 -> ArgentinaRepuestos | D9: 0.14 | F9: Ecuador | G9: 12 Cuotas | H9: =F9&G9 -> Ecuador12 Cuotas | I9: 0.02 | K9: Cuotas Int. Bajo
A10: Argentina | B10: Tecnología | C10: =A10&B10 -> ArgentinaTecnología | D10: 0.12 | F10: Colombia | G10: 12 Cuotas | H10: =F10&G10 -> Colombia12 Cuotas | I10: 0.04
A11: Argentina | B11: Electro | C11: =A11&B11 -> ArgentinaElectro | D11: 0.145 | F11: Pais | G11: Valor Envío
A12: Argentina | B12: Juguetería | C12: =A12&B12 -> ArgentinaJuguetería | D12: 0.145 | F12: Argentina | G12: 12000
A13: Argentina | B13: Construcción | C13: =A13&B13 -> ArgentinaConstrucción | D13: 0.145 | F13: Uruguay | G13: 200
A14: Argentina | B14: Belleza y Cuidado | C14: =A14&B14 -> ArgentinaBelleza y Cuidado | D14: 0.15 | F14: Ecuador | G14: 2.5
A15: Argentina | B15: Deportes | C15: =A15&B15 -> ArgentinaDeportes | D15: 0.135 | F15: Colombia | G15: 8000
A16: Argentina | B16: Accesorios Vehiculos | C16: =A16&B16 -> ArgentinaAccesorios Vehiculos | D16: 0.145 | F16: Pais | G16: Mínimo para Envío
A17: Argentina | B17: Autopartes | C17: =A17&B17 -> ArgentinaAutopartes | D17: 0.145
A18: Argentina | B18: Hogar, muebles y jardín | C18: =A18&B18 -> ArgentinaHogar, muebles y jardín | D18: 0.14 | F18: Argentina | G18: 33000
A19: Argentina | B19: Ropa & Acc | C19: =A19&B19 -> ArgentinaRopa & Acc | D19: 0.135 | F19: Uruguay | G19: 1200
A20: Uruguay | B20: Zapatillas | C20: =A19&B20 -> ArgentinaZapatillas | D20: 0.145 | F20: Ecuador | G20: 10
A21: Uruguay | B21: Autopartes | C21: =A20&B21 -> UruguayAutopartes | D21: 0.15 | F21: Colombia | G21: 60000
A22: Uruguay | B22: Tecnología | C22: =A21&B22 -> UruguayTecnología | D22: 0.14 | F22: Pais | G22: Costo Fijo
A23: Uruguay | B23: Electro | C23: =A22&B23 -> UruguayElectro | D23: 0.14 | F23: Argentina | G23: 2628
A24: Uruguay | B24: Construcción | C24: =A23&B24 -> UruguayConstrucción | D24: 0.145 | F24: Uruguay | G24: 29
A25: Uruguay | B25: Belleza y Cuidado | C25: =A25&B25 -> UruguayBelleza y Cuidado | D25: 0.135 | F25: Ecuador | G25: 0
A26: Ecuador | B26: Deportes | C26: =A28&B26 -> UruguayDeportes | D26: 0.145 | F26: Colombia | G26: 4000
A27: Colombia | B27: Moda | C27: =A27&B27 -> ColombiaModa | D27: 0.155
A28: Uruguay | B28: Salud y equipmaientos médicos | C28: =A28&B28 -> UruguaySalud y equipmaientos médicos | D28: 0.155
A29: Ecuador | B29: Autopartes | C29: =A26&B29 -> EcuadorAutopartes | D29: 0.12 | F29: Argentina | G29: Costos Fijos | H29: Uruguay | I29: Costos Fijos
A30: Colombia | B30: Autopartes | C30: =A27&B30 -> ColombiaAutopartes | D30: 0.15 | F30: 15000 | G30: 1095 | H30: 400 | I30: 9
F31: $15000 / $25000 | G31: 2190 | H31: 400 / 800 | I31: 16
F32: $25000 / $33000 | G32: 2628 | H32: 800 / 1200 | I32: 29
F33: 33000 | G33: 0

Sheet Directa
A1: Sku | B1: Producto 1 | C1: % | E1: Sku | F1: Producto 2 | G1: % | I1: Diferencia
A2: País | B2: Argentina | E2: País | F2: Argentina
A3: Vertical | B3: Construcción | E3: Vertical | F3: Construcción
A4: Tipo de Publicación | B4: Clásica | C4: =IFERROR(IF(B4="Clásica",((VLOOKUP(B2&B3,Datos!C:D,2,0))),(VLOOKUP(B2&B3,Datos!C:D,2,0)+VLOOKUP(B2&B4,Datos!H:I,2,0))),"Tipo Public. Invalida") -> 0.145 | E4: Tipo de Publicación | F4: Clásica | G4: =IFERROR(IF(F4="Clásica",((VLOOKUP(F2&F3,Datos!C:D,2,0))),(VLOOKUP(F2&F3,Datos!C:D,2,0)+VLOOKUP(F2&F4,Datos!H:I,2,0))),"Tipo Public. Invalida") -> 0.145
A5: Precio de Venta (con Iva) | B5: 250000 | E5: Precio de Venta (con Iva) | F5: 34110 | I5: =F5/B5 -> 0.13644
A6: Costo (con Iva) | B6: -133000 | E6: Costo (con Iva) | F6: -14239.895
A7: Iva Venta | B7: =IF($B$2="Argentina", -B5/(1+C7)*C7, -B5/(1+VLOOKUP($B$2,Datos!$A$2:$B$5,2,FALSE()))*VLOOKUP($B$2,Datos!$A$2:$B$5,2,FALSE())) -> -23755.656 | C7: 0.105 | E7: Iva Venta | F7: =IF($B$2="Argentina", -F5/(1+G7)*G7, -F5/(1+VLOOKUP($B$2,Datos!$A$2:$B$5,2,FALSE()))*VLOOKUP($B$2,Datos!$A$2:$B$5,2,FALSE())) -> -5919.9174 | G7: 0.21 | J7: =+F5/B5 -> 0.13644
A8: Iva Compra | B8: =IF($B$2="Argentina", -B6/(1+C8)*C8, -B6/(1+VLOOKUP($B$2,Datos!$A$2:$B$5,2,FALSE()))*VLOOKUP($B$2,Datos!$A$2:$B$5,2,FALSE())) -> 12638.009 | C8: 0.105 | E8: Iva Compra | F8: =IF($B$2="Argentina", -F6/(1+G8)*G8, -F6/(1+VLOOKUP($B$2,Datos!$A$2:$B$5,2,FALSE()))*VLOOKUP($B$2,Datos!$A$2:$B$5,2,FALSE())) -> 2471.3867 | G8: 0.21
A9: Comisión | B9: =IFERROR(-((B5*(IF(B4="Clásica",((VLOOKUP(B2&B3,Datos!C:D,2,0))),(VLOOKUP(B2&B3,Datos!C:D,2,0)+VLOOKUP(B2&B4,Datos!H:I,2,0)))))),"Error") -> -36250 | C9: =IFERROR(IF(B4="Clásica",((VLOOKUP(B2&B3,Datos!C:D,2,0))),(VLOOKUP(B2&B3,Datos!C:D,2,0)+VLOOKUP(B2&B4,Datos!H:I,2,0))),"Error") -> 0.145 | E9: Comisión | F9: =IFERROR(-((F5*(IF(F4="Clásica",((VLOOKUP(F2&F3,Datos!C:D,2,0))),(VLOOKUP(F2&F3,Datos!C:D,2,0)+VLOOKUP(F2&F4,Datos!H:I,2,0)))))),"Error") -> -4945.95 | G9: =IFERROR(IF(F4="Clásica",((VLOOKUP(F2&F3,Datos!C:D,2,0))),(VLOOKUP(F2&F3,Datos!C:D,2,0)+VLOOKUP(F2&F4,Datos!H:I,2,0))),"Error") -> 0.145
A10: Iva Comisión | B10: =IFERROR(-(B9-(B9/(1+VLOOKUP(B2,Datos!A1:B5,2,0)))),0) -> 6291.3223 | C10: =VLOOKUP(B2,Datos!A1:B5,2,0) -> 0.21 | E10: Iva Comisión | F10: =IFERROR(-(F9-(F9/(1+VLOOKUP(F2,Datos!A1:B5,2,0)))),0) -> 858.38802 | G10: =VLOOKUP(F2,Datos!A1:B5,2,0) -> 0.21
A11: Costo Fijo | B11: =IF(B2="Argentina", IF(B5<=15000, -1000, IF(B5<=25000, -2000, IF(B5<=33000, -2400, 0))), IF(B2="Uruguay", IF(B5<=400, -9, IF(B5<=800, -16, IF(B5<=1200, -29, 0))), -VLOOKUP(B2, Datos!F22:G26, 2, FALSE()))) -> 0 | E11: Costo Fijo | F11: =IF(F2="Argentina", IF(F5<=15000, -1000, IF(F5<=25000, -2000, IF(F5<=33000, -2400, 0))), IF(F2="Uruguay", IF(F5<=400, -9, IF(F5<=800, -16, IF(F5<=1200, -29, 0))), -VLOOKUP(F2, Datos!J22:K26, 2, FALSE()))) -> 0
A12: Iva Costo Fijo | B12: =-(B11-(B11/(1+VLOOKUP(B2,Datos!A1:B5,2,0)))) -> 0 | C12: =VLOOKUP(B2,Datos!A1:B5,2,0) -> 0.21 | E12: Iva Costo Fijo | F12: =-(F11-(F11/(1+VLOOKUP(F2,Datos!A1:B5,2,0)))) -> 0 | G12: =VLOOKUP(F2,Datos!A1:B5,2,0) -> 0.21
A13: Envío | B13: -9000 | C13: PONER MANUAL | E13: Envío | F13: -7000
A14: Iva Envío Compra | B14: =IFERROR(-(B13-(B13/(1+VLOOKUP(B2,Datos!A1:B5,2,0)))),0) -> 1561.9835 | C14: =VLOOKUP(B2,Datos!A1:B5,2,0) -> 0.21 | E14: Iva Envío Compra | F14: =IFERROR(-(F13-(F13/(1+VLOOKUP(F2,Datos!A1:B5,2,0)))),0) -> 1214.876 | G14: =VLOOKUP(F2,Datos!A1:B5,2,0) -> 0.21
A15: Otros Impuestos | B15: =IFERROR(-(B5*VLOOKUP(B2,Datos!A1:C5,3,0)),0) -> -11750 | C15: 0.045 | E15: Otros Impuestos | F15: =IFERROR(-(F5*VLOOKUP(F2,Datos!A1:C5,3,0)),0) -> -1603.17 | G15: =IFERROR(VLOOKUP(F2,Datos!A1:C5,3,0),0) -> 0.047
A16: Plata en Mano | B16: =IFERROR(B5+B8+B7+B9+B10+B11+B12+B13+B14+B15,"Error") -> 189735.66 | E16: Plata en Mano | F16: =IFERROR(F5+F8+F7+F9+F10+F11+F12+F13+F14+F15,"Error") -> 19185.613
A17: Utilidad | B17: =IF(B16="Error","Error",SUM(B5:B15)) -> 56735.659 | C17: =B17/(B5+B7) -> 0.25077161 | E17: Utilidad | F17: =IF(F16="Error","Error",SUM(F5:F15)) -> 4945.7187 | G17: =F17/(F5+F7) -> 0.1754418
A19: MarkUp | B19: =-B5/B6 -> 1.8796992 | E19: MarkUp | F19: =-F5/F6 -> 2.3953829
C20: =+B5+B6 -> 117000
A21: =VLOOKUP(B2,Datos!A1:D5,4,0) -> https://www.mercadolibre.com.ar/simulador-de-costos?
G23: 3 | I23: 9
C24: =+C20/B5 -> 0.468 | F24: 1 | G24: 6 | I24: 12

Sheet Productos
A1: SKU | B1: PRODUCTO | C1: COSTO ( SIN IVA ) | D1: IVA | E1: COSTO TOTAL ( C/IVA) | F1: PROVEEDOR | G1: Nota | H1: USD | J1: Vertical ML | K1: Tipo de publicación | L1: IVA venta | M1: Precio de venta (c/IVA) | N1: Envío (costo, en positivo) | O1: Comisión % | P1: Comisión | Q1: IVA comisión | R1: Costo fijo | S1: IVA costo fijo | T1: IVA venta $ | U1: IVA compra $ | V1: Envío | W1: IVA envío | X1: Otros impuestos | Y1: Plata en mano | Z1: Utilidad | AA1: Margen % | AB1: MarkUp | AD1: Precio más bajo ML (c/IVA) | AE1: Publicación de referencia | AF1: Margen objetivo | AG1: Margen a precio ML con costo actual | AH1: Costo máximo (s/IVA) para precio ML | AI1: Costo máximo (c/IVA) | AJ1: Costo actual vs máximo | AK1: Estado
A2: 1200326 | B2: Sopla-Aspirador Pampa Pro 26cc SPP-26 | C2: 121227.94 | D2: 0.105 | E2: =+C2*(1+D2) -> 133956.87 | F2: RUMBO SRL | G2: Costo con flete bonificado por cantidad ( RUMBO) + dto pago contado | H2: 1600 | J2: Hogar, muebles y jardín | K2: Clásica | L2: 0.105 | M2: 180000 | N2: 0 | O2: =IF($M2="","",IFERROR(IF($K2="Clásica",VLOOKUP("Argentina"&$J2,Datos!$C:$D,2,0),VLOOKUP("Argentina"&$J2,Datos!$C:$D,2,0)+VLOOKUP("Argentina"&$K2,Datos!$H:$I,2,0)),"Error")) -> 0.14 | P2: =IF($M2="","",IFERROR(-$M2*$O2,"Error")) -> -25200 | Q2: =IF($M2="","",IFERROR(-($P2-$P2/(1+Datos!$B$2)),"Error")) -> 4373.5537 | R2: =IF($M2="","",IF($M2<=15000,-1000,IF($M2<=25000,-2000,IF($M2<=33000,-2400,0)))) -> 0 | S2: =IF($M2="","",-($R2-$R2/(1+Datos!$B$2))) -> 0 | T2: =IF($M2="","",-$M2/(1+$L2)*$L2) -> -17104.072 | U2: =IF($M2="","",$C2*$D2) -> 12728.934 | V2: =IF($M2="","",-N($N2)) -> 0 | W2: =IF($M2="","",-($V2-$V2/(1+Datos!$B$2))) -> 0 | X2: =IF($M2="","",-$M2*Datos!$C$2) -> -8460 | Y2: =IF($M2="","",IFERROR($M2+$U2+$T2+$P2+$Q2+$R2+$S2+$V2+$W2+$X2,"Error")) -> 146338.42 | Z2: =IF($M2="","",IFERROR($Y2-$E2,"Error")) -> 12381.541 | AA2: =IF($M2="","",IFERROR($Z2/($M2+$T2),"Error")) -> 0.076008906 | AB2: =IF($M2="","",IFERROR($M2/$E2,"Error")) -> 1.343716 | AD2: 180000 | AE2: Sopladora Aspiradora A Explosión 26cc Pampa Pro · 10 u. | AF2: 0.15 | AG2: =IF(N($AD2)=0,"",IFERROR(($AD2/(1+$L2)-($AD2*$O2+IF($AD2<=15000,1000,IF($AD2<=25000,2000,IF($AD2<=33000,2400,0)))+N($N2))/(1+Datos!$B$2)-$AD2*Datos!$C$2-$C2)/($AD2/(1+$L2)),"Error")) -> 0.076008906 | AH2: =IF(N($AD2)=0,"",IFERROR($AD2/(1+$L2)*(1-$AF2)-($AD2*$O2+IF($AD2<=15000,1000,IF($AD2<=25000,2000,IF($AD2<=33000,2400,0)))+N($N2))/(1+Datos!$B$2)-$AD2*Datos!$C$2,"Error")) -> 109175.09 | AI2: =IF($AH2="","",IFERROR($AH2*(1+$D2),"Error")) -> 120638.48 | AJ2: =IF($AH2="","",IFERROR($C2/$AH2-1,"Error")) -> 0.11039925 | AK2: =IF($AH2="","",IFERROR(IF($C2<=$AH2,"OK a ese precio","Bajar costo"),"Error")) -> Bajar costo
A3: 1035606 | B3: Motor vertical Niwa 6,5HP 201cc MVNW-201 | C3: 186919.36 | D3: 0.105 | E3: =+C3*(1+D3) -> 206545.89 | F3: RUMBO SRL | G3: Costo con flete bonificado por cantidad ( RUMBO) + dto pago contado | H3: 1600 | J3: Hogar, muebles y jardín | K3: Clásica | L3: 0.105 | M3: 308889 | N3: 0 | O3: =IF($M3="","",IFERROR(IF($K3="Clásica",VLOOKUP("Argentina"&$J3,Datos!$C:$D,2,0),VLOOKUP("Argentina"&$J3,Datos!$C:$D,2,0)+VLOOKUP("Argentina"&$K3,Datos!$H:$I,2,0)),"Error")) -> 0.14 | P3: =IF($M3="","",IFERROR(-$M3*$O3,"Error")) -> -43244.46 | Q3: =IF($M3="","",IFERROR(-($P3-$P3/(1+Datos!$B$2)),"Error")) -> 7505.2369 | R3: =IF($M3="","",IF($M3<=15000,-1000,IF($M3<=25000,-2000,IF($M3<=33000,-2400,0)))) -> 0 | S3: =IF($M3="","",-($R3-$R3/(1+Datos!$B$2))) -> 0 | T3: =IF($M3="","",-$M3/(1+$L3)*$L3) -> -29351.443 | U3: =IF($M3="","",$C3*$D3) -> 19626.533 | V3: =IF($M3="","",-N($N3)) -> 0 | W3: =IF($M3="","",-($V3-$V3/(1+Datos!$B$2))) -> 0 | X3: =IF($M3="","",-$M3*Datos!$C$2) -> -14517.783 | Y3: =IF($M3="","",IFERROR($M3+$U3+$T3+$P3+$Q3+$R3+$S3+$V3+$W3+$X3,"Error")) -> 248907.08 | Z3: =IF($M3="","",IFERROR($Y3-$E3,"Error")) -> 42361.19 | AA3: =IF($M3="","",IFERROR($Z3/($M3+$T3),"Error")) -> 0.15154025 | AB3: =IF($M3="","",IFERROR($M3/$E3,"Error")) -> 1.4954981 | AD3: 308889 | AE3: Motor Niwa Cortacésped 6,5hp Tipo Briggs · 90 u. | AF3: 0.15 | AG3: =IF(N($AD3)=0,"",IFERROR(($AD3/(1+$L3)-($AD3*$O3+IF($AD3<=15000,1000,IF($AD3<=25000,2000,IF($AD3<=33000,2400,0)))+N($N3))/(1+Datos!$B$2)-$AD3*Datos!$C$2-$C3)/($AD3/(1+$L3)),"Error")) -> 0.15154025 | AH3: =IF(N($AD3)=0,"",IFERROR($AD3/(1+$L3)*(1-$AF3)-($AD3*$O3+IF($AD3<=15000,1000,IF($AD3<=25000,2000,IF($AD3<=33000,2400,0)))+N($N3))/(1+Datos!$B$2)-$AD3*Datos!$C$2,"Error")) -> 187349.92 | AI3: =IF($AH3="","",IFERROR($AH3*(1+$D3),"Error")) -> 207021.66 | AJ3: =IF($AH3="","",IFERROR($C3/$AH3-1,"Error")) -> -0.0022981432 | AK3: =IF($AH3="","",IFERROR(IF($C3<=$AH3,"OK a ese precio","Bajar costo"),"Error")) -> OK a ese precio
A4: 1035604 | B4: Motor vertical Niwa 4,5HP 149cc MVNW-149 | C4: 144526.25 | D4: 0.105 | E4: =+C4*(1+D4) -> 159701.51 | F4: RUMBO SRL | G4: Costo con flete bonificado por cantidad ( RUMBO) + dto pago contado | H4: 1600 | J4: Hogar, muebles y jardín | K4: Clásica | L4: 0.105 | M4: 195000 | N4: 0 | O4: =IF($M4="","",IFERROR(IF($K4="Clásica",VLOOKUP("Argentina"&$J4,Datos!$C:$D,2,0),VLOOKUP("Argentina"&$J4,Datos!$C:$D,2,0)+VLOOKUP("Argentina"&$K4,Datos!$H:$I,2,0)),"Error")) -> 0.14 | P4: =IF($M4="","",IFERROR(-$M4*$O4,"Error")) -> -27300 | Q4: =IF($M4="","",IFERROR(-($P4-$P4/(1+Datos!$B$2)),"Error")) -> 4738.0165 | R4: =IF($M4="","",IF($M4<=15000,-1000,IF($M4<=25000,-2000,IF($M4<=33000,-2400,0)))) -> 0 | S4: =IF($M4="","",-($R4-$R4/(1+Datos!$B$2))) -> 0 | T4: =IF($M4="","",-$M4/(1+$L4)*$L4) -> -18529.412 | U4: =IF($M4="","",$C4*$D4) -> 15175.256 | V4: =IF($M4="","",-N($N4)) -> 0 | W4: =IF($M4="","",-($V4-$V4/(1+Datos!$B$2))) -> 0 | X4: =IF($M4="","",-$M4*Datos!$C$2) -> -9165 | Y4: =IF($M4="","",IFERROR($M4+$U4+$T4+$P4+$Q4+$R4+$S4+$V4+$W4+$X4,"Error")) -> 159918.86 | Z4: =IF($M4="","",IFERROR($Y4-$E4,"Error")) -> 217.35476 | AA4: =IF($M4="","",IFERROR($Z4/($M4+$T4),"Error")) -> 0.001231677 | AB4: =IF($M4="","",IFERROR($M4/$E4,"Error")) -> 1.2210279 | AD4: 195000 | AE4: Motor Vertical Niwa Mvnw-149 4.5 Hp · 20 u. | AF4: 0.15 | AG4: =IF(N($AD4)=0,"",IFERROR(($AD4/(1+$L4)-($AD4*$O4+IF($AD4<=15000,1000,IF($AD4<=25000,2000,IF($AD4<=33000,2400,0)))+N($N4))/(1+Datos!$B$2)-$AD4*Datos!$C$2-$C4)/($AD4/(1+$L4)),"Error")) -> 0.001231677 | AH4: =IF(N($AD4)=0,"",IFERROR($AD4/(1+$L4)*(1-$AF4)-($AD4*$O4+IF($AD4<=15000,1000,IF($AD4<=25000,2000,IF($AD4<=33000,2400,0)))+N($N4))/(1+Datos!$B$2)-$AD4*Datos!$C$2,"Error")) -> 118273.02 | AI4: =IF($AH4="","",IFERROR($AH4*(1+$D4),"Error")) -> 130691.68 | AJ4: =IF($AH4="","",IFERROR($C4/$AH4-1,"Error")) -> 0.22197145 | AK4: =IF($AH4="","",IFERROR(IF($C4<=$AH4,"OK a ese precio","Bajar costo"),"Error")) -> Bajar costo
A5: KCC1400E | B5: Cortadora de césped Eléctrica KONAN 1400W IC04124874U | C5: 125549.76 | D5: 0.21 | E5: =+C5*(1+D5) -> 151915.21 | F5: RUMBO SRL | G5: Costo con flete bonificado por cantidad ( RUMBO) + dto pago contado | H5: 1600 | J5: Hogar, muebles y jardín | K5: Clásica | L5: 0.21 | M5: 173000 | N5: 0 | O5: =IF($M5="","",IFERROR(IF($K5="Clásica",VLOOKUP("Argentina"&$J5,Datos!$C:$D,2,0),VLOOKUP("Argentina"&$J5,Datos!$C:$D,2,0)+VLOOKUP("Argentina"&$K5,Datos!$H:$I,2,0)),"Error")) -> 0.14 | P5: =IF($M5="","",IFERROR(-$M5*$O5,"Error")) -> -24220 | Q5: =IF($M5="","",IFERROR(-($P5-$P5/(1+Datos!$B$2)),"Error")) -> 4203.4711 | R5: =IF($M5="","",IF($M5<=15000,-1000,IF($M5<=25000,-2000,IF($M5<=33000,-2400,0)))) -> 0 | S5: =IF($M5="","",-($R5-$R5/(1+Datos!$B$2))) -> 0 | T5: =IF($M5="","",-$M5/(1+$L5)*$L5) -> -30024.793 | U5: =IF($M5="","",$C5*$D5) -> 26365.45 | V5: =IF($M5="","",-N($N5)) -> 0 | W5: =IF($M5="","",-($V5-$V5/(1+Datos!$B$2))) -> 0 | X5: =IF($M5="","",-$M5*Datos!$C$2) -> -8131 | Y5: =IF($M5="","",IFERROR($M5+$U5+$T5+$P5+$Q5+$R5+$S5+$V5+$W5+$X5,"Error")) -> 141193.13 | Z5: =IF($M5="","",IFERROR($Y5-$E5,"Error")) -> -10722.082 | AA5: =IF($M5="","",IFERROR($Z5/($M5+$T5),"Error")) -> -0.074992599 | AB5: =IF($M5="","",IFERROR($M5/$E5,"Error")) -> 1.1387931 | AD5: 173000 | AE5: Cortadora Césped Eléctrica Konan 1400w · 2 u. | AF5: 0.15 | AG5: =IF(N($AD5)=0,"",IFERROR(($AD5/(1+$L5)-($AD5*$O5+IF($AD5<=15000,1000,IF($AD5<=25000,2000,IF($AD5<=33000,2400,0)))+N($N5))/(1+Datos!$B$2)-$AD5*Datos!$C$2-$C5)/($AD5/(1+$L5)),"Error")) -> -0.074992599 | AH5: =IF(N($AD5)=0,"",IFERROR($AD5/(1+$L5)*(1-$AF5)-($AD5*$O5+IF($AD5<=15000,1000,IF($AD5<=25000,2000,IF($AD5<=33000,2400,0)))+N($N5))/(1+Datos!$B$2)-$AD5*Datos!$C$2,"Error")) -> 93381.397 | AI5: =IF($AH5="","",IFERROR($AH5*(1+$D5),"Error")) -> 112991.49 | AJ5: =IF($AH5="","",IFERROR($C5/$AH5-1,"Error")) -> 0.34448364 | AK5: =IF($AH5="","",IFERROR(IF($C5<=$AH5,"OK a ese precio","Bajar costo"),"Error")) -> Bajar costo
A6: FC1111410 | B6: FIASA 18" RA Ruedas Altas 11" C/rulemanes ZONGSHEN XP XP140- 140CC | C6: 350340.9 | D6: 0.21 | E6: =+C6*(1+D6) -> 423912.49 | F6: FIASA | G6: Costo incluido Fletes ( FIASA ) | H6: 1565 | J6: Hogar, muebles y jardín | K6: Clásica | L6: 0.21 | M6: 480000 | N6: 0 | O6: =IF($M6="","",IFERROR(IF($K6="Clásica",VLOOKUP("Argentina"&$J6,Datos!$C:$D,2,0),VLOOKUP("Argentina"&$J6,Datos!$C:$D,2,0)+VLOOKUP("Argentina"&$K6,Datos!$H:$I,2,0)),"Error")) -> 0.14 | P6: =IF($M6="","",IFERROR(-$M6*$O6,"Error")) -> -67200 | Q6: =IF($M6="","",IFERROR(-($P6-$P6/(1+Datos!$B$2)),"Error")) -> 11662.81 | R6: =IF($M6="","",IF($M6<=15000,-1000,IF($M6<=25000,-2000,IF($M6<=33000,-2400,0)))) -> 0 | S6: =IF($M6="","",-($R6-$R6/(1+Datos!$B$2))) -> 0 | T6: =IF($M6="","",-$M6/(1+$L6)*$L6) -> -83305.785 | U6: =IF($M6="","",$C6*$D6) -> 73571.589 | V6: =IF($M6="","",-N($N6)) -> 0 | W6: =IF($M6="","",-($V6-$V6/(1+Datos!$B$2))) -> 0 | X6: =IF($M6="","",-$M6*Datos!$C$2) -> -22560 | Y6: =IF($M6="","",IFERROR($M6+$U6+$T6+$P6+$Q6+$R6+$S6+$V6+$W6+$X6,"Error")) -> 392168.61 | Z6: =IF($M6="","",IFERROR($Y6-$E6,"Error")) -> -31743.875 | AA6: =IF($M6="","",IFERROR($Z6/($M6+$T6),"Error")) -> -0.080021019 | AB6: =IF($M6="","",IFERROR($M6/$E6,"Error")) -> 1.1323092 | AD6: 480000 | AE6: Cortadora Césped Nafta Fiasa Fc1111410 140cc 46cm · 5 u. | AF6: 0.15 | AG6: =IF(N($AD6)=0,"",IFERROR(($AD6/(1+$L6)-($AD6*$O6+IF($AD6<=15000,1000,IF($AD6<=25000,2000,IF($AD6<=33000,2400,0)))+N($N6))/(1+Datos!$B$2)-$AD6*Datos!$C$2-$C6)/($AD6/(1+$L6)),"Error")) -> -0.080021019 | AH6: =IF(N($AD6)=0,"",IFERROR($AD6/(1+$L6)*(1-$AF6)-($AD6*$O6+IF($AD6<=15000,1000,IF($AD6<=25000,2000,IF($AD6<=33000,2400,0)))+N($N6))/(1+Datos!$B$2)-$AD6*Datos!$C$2,"Error")) -> 259092.89 | AI6: =IF($AH6="","",IFERROR($AH6*(1+$D6),"Error")) -> 313502.4 | AJ6: =IF($AH6="","",IFERROR($C6/$AH6-1,"Error")) -> 0.3521826 | AK6: =IF($AH6="","",IFERROR(IF($C6<=$AH6,"OK a ese precio","Bajar costo"),"Error")) -> Bajar costo
A7: FC1111700 | B7: OLEO MAC 20" RA Ruedas Altas 11" C/rulemanes ZONGSHEN XP 200 196 CC | C7: 441106 | D7: 0.21 | E7: =+C7*(1+D7) -> 533738.26 | F7: FIASA | G7: Costo incluido Fletes ( FIASA ) | H7: 1565 | J7: Hogar, muebles y jardín | K7: Clásica | L7: 0.21 | M7: 750000 | N7: 0 | O7: =IF($M7="","",IFERROR(IF($K7="Clásica",VLOOKUP("Argentina"&$J7,Datos!$C:$D,2,0),VLOOKUP("Argentina"&$J7,Datos!$C:$D,2,0)+VLOOKUP("Argentina"&$K7,Datos!$H:$I,2,0)),"Error")) -> 0.14 | P7: =IF($M7="","",IFERROR(-$M7*$O7,"Error")) -> -105000 | Q7: =IF($M7="","",IFERROR(-($P7-$P7/(1+Datos!$B$2)),"Error")) -> 18223.14 | R7: =IF($M7="","",IF($M7<=15000,-1000,IF($M7<=25000,-2000,IF($M7<=33000,-2400,0)))) -> 0 | S7: =IF($M7="","",-($R7-$R7/(1+Datos!$B$2))) -> 0 | T7: =IF($M7="","",-$M7/(1+$L7)*$L7) -> -130165.29 | U7: =IF($M7="","",$C7*$D7) -> 92632.26 | V7: =IF($M7="","",-N($N7)) -> 0 | W7: =IF($M7="","",-($V7-$V7/(1+Datos!$B$2))) -> 0 | X7: =IF($M7="","",-$M7*Datos!$C$2) -> -35250 | Y7: =IF($M7="","",IFERROR($M7+$U7+$T7+$P7+$Q7+$R7+$S7+$V7+$W7+$X7,"Error")) -> 590440.11 | Z7: =IF($M7="","",IFERROR($Y7-$E7,"Error")) -> 56701.851 | AA7: =IF($M7="","",IFERROR($Z7/($M7+$T7),"Error")) -> 0.091478987 | AB7: =IF($M7="","",IFERROR($M7/$E7,"Error")) -> 1.4051831 | AD7: 750000 | AE7: Cortadora De Césped Naftera Oleo-mac® FC1111700 · 2 u. | AF7: 0.15 | AG7: =IF(N($AD7)=0,"",IFERROR(($AD7/(1+$L7)-($AD7*$O7+IF($AD7<=15000,1000,IF($AD7<=25000,2000,IF($AD7<=33000,2400,0)))+N($N7))/(1+Datos!$B$2)-$AD7*Datos!$C$2-$C7)/($AD7/(1+$L7)),"Error")) -> 0.091478987 | AH7: =IF(N($AD7)=0,"",IFERROR($AD7/(1+$L7)*(1-$AF7)-($AD7*$O7+IF($AD7<=15000,1000,IF($AD7<=25000,2000,IF($AD7<=33000,2400,0)))+N($N7))/(1+Datos!$B$2)-$AD7*Datos!$C$2,"Error")) -> 404832.64 | AI7: =IF($AH7="","",IFERROR($AH7*(1+$D7),"Error")) -> 489847.5 | AJ7: =IF($AH7="","",IFERROR($C7/$AH7-1,"Error")) -> 0.089600866 | AK7: =IF($AH7="","",IFERROR(IF($C7<=$AH7,"OK a ese precio","Bajar costo"),"Error")) -> Bajar costo
A8: FC742-5555 | B8: FC742-5555 CUCHILLA 20 OM AUT | C8: 15566.49 | D8: 0.21 | E8: =+C8*(1+D8) -> 18835.453 | F8: FIASA | G8: Costo incluido Fletes ( FIASA ) | H8: 1565 | J8: Hogar, muebles y jardín | K8: Clásica | L8: 0.21 | N8: 0 | O8: =IF($M8="","",IFERROR(IF($K8="Clásica",VLOOKUP("Argentina"&$J8,Datos!$C:$D,2,0),VLOOKUP("Argentina"&$J8,Datos!$C:$D,2,0)+VLOOKUP("Argentina"&$K8,Datos!$H:$I,2,0)),"Error")) | P8: =IF($M8="","",IFERROR(-$M8*$O8,"Error")) | Q8: =IF($M8="","",IFERROR(-($P8-$P8/(1+Datos!$B$2)),"Error")) | R8: =IF($M8="","",IF($M8<=15000,-1000,IF($M8<=25000,-2000,IF($M8<=33000,-2400,0)))) | S8: =IF($M8="","",-($R8-$R8/(1+Datos!$B$2))) | T8: =IF($M8="","",-$M8/(1+$L8)*$L8) | U8: =IF($M8="","",$C8*$D8) | V8: =IF($M8="","",-N($N8)) | W8: =IF($M8="","",-($V8-$V8/(1+Datos!$B$2))) | X8: =IF($M8="","",-$M8*Datos!$C$2) | Y8: =IF($M8="","",IFERROR($M8+$U8+$T8+$P8+$Q8+$R8+$S8+$V8+$W8+$X8,"Error")) | Z8: =IF($M8="","",IFERROR($Y8-$E8,"Error")) | AA8: =IF($M8="","",IFERROR($Z8/($M8+$T8),"Error")) | AB8: =IF($M8="","",IFERROR($M8/$E8,"Error")) | AE8: Sin referencia en el export: cargar precio de ML | AF8: 0.15 | AG8: =IF(N($AD8)=0,"",IFERROR(($AD8/(1+$L8)-($AD8*$O8+IF($AD8<=15000,1000,IF($AD8<=25000,2000,IF($AD8<=33000,2400,0)))+N($N8))/(1+Datos!$B$2)-$AD8*Datos!$C$2-$C8)/($AD8/(1+$L8)),"Error")) | AH8: =IF(N($AD8)=0,"",IFERROR($AD8/(1+$L8)*(1-$AF8)-($AD8*$O8+IF($AD8<=15000,1000,IF($AD8<=25000,2000,IF($AD8<=33000,2400,0)))+N($N8))/(1+Datos!$B$2)-$AD8*Datos!$C$2,"Error")) | AI8: =IF($AH8="","",IFERROR($AH8*(1+$D8),"Error")) | AJ8: =IF($AH8="","",IFERROR($C8/$AH8-1,"Error")) | AK8: =IF($AH8="","",IFERROR(IF($C8<=$AH8,"OK a ese precio","Bajar costo"),"Error"))
A9: FC66020047 | B9: FC66020047 CUCHILLA 43 ELECTRIC | C9: 12320 | D9: 0.21 | E9: =+C9*(1+D9) -> 14907.2 | F9: FIASA | G9: Costo incluido Fletes ( FIASA ) | H9: 1565 | J9: Hogar, muebles y jardín | K9: Clásica | L9: 0.21 | N9: 0 | O9: =IF($M9="","",IFERROR(IF($K9="Clásica",VLOOKUP("Argentina"&$J9,Datos!$C:$D,2,0),VLOOKUP("Argentina"&$J9,Datos!$C:$D,2,0)+VLOOKUP("Argentina"&$K9,Datos!$H:$I,2,0)),"Error")) | P9: =IF($M9="","",IFERROR(-$M9*$O9,"Error")) | Q9: =IF($M9="","",IFERROR(-($P9-$P9/(1+Datos!$B$2)),"Error")) | R9: =IF($M9="","",IF($M9<=15000,-1000,IF($M9<=25000,-2000,IF($M9<=33000,-2400,0)))) | S9: =IF($M9="","",-($R9-$R9/(1+Datos!$B$2))) | T9: =IF($M9="","",-$M9/(1+$L9)*$L9) | U9: =IF($M9="","",$C9*$D9) | V9: =IF($M9="","",-N($N9)) | W9: =IF($M9="","",-($V9-$V9/(1+Datos!$B$2))) | X9: =IF($M9="","",-$M9*Datos!$C$2) | Y9: =IF($M9="","",IFERROR($M9+$U9+$T9+$P9+$Q9+$R9+$S9+$V9+$W9+$X9,"Error")) | Z9: =IF($M9="","",IFERROR($Y9-$E9,"Error")) | AA9: =IF($M9="","",IFERROR($Z9/($M9+$T9),"Error")) | AB9: =IF($M9="","",IFERROR($M9/$E9,"Error")) | AE9: Sin referencia en el export: cargar precio de ML | AF9: 0.15 | AG9: =IF(N($AD9)=0,"",IFERROR(($AD9/(1+$L9)-($AD9*$O9+IF($AD9<=15000,1000,IF($AD9<=25000,2000,IF($AD9<=33000,2400,0)))+N($N9))/(1+Datos!$B$2)-$AD9*Datos!$C$2-$C9)/($AD9/(1+$L9)),"Error")) | AH9: =IF(N($AD9)=0,"",IFERROR($AD9/(1+$L9)*(1-$AF9)-($AD9*$O9+IF($AD9<=15000,1000,IF($AD9<=25000,2000,IF($AD9<=33000,2400,0)))+N($N9))/(1+Datos!$B$2)-$AD9*Datos!$C$2,"Error")) | AI9: =IF($AH9="","",IFERROR($AH9*(1+$D9),"Error")) | AJ9: =IF($AH9="","",IFERROR($C9/$AH9-1,"Error")) | AK9: =IF($AH9="","",IFERROR(IF($C9<=$AH9,"OK a ese precio","Bajar costo"),"Error"))
A10: FC66040017 | B10: CUCHILLA 47 | C10: 13608 | D10: 0.21 | E10: =+C10*(1+D10) -> 16465.68 | F10: FIASA | G10: Costo incluido Fletes ( FIASA ) | H10: 1565 | J10: Hogar, muebles y jardín | K10: Clásica | L10: 0.21 | M10: 25700 | N10: 0 | O10: =IF($M10="","",IFERROR(IF($K10="Clásica",VLOOKUP("Argentina"&$J10,Datos!$C:$D,2,0),VLOOKUP("Argentina"&$J10,Datos!$C:$D,2,0)+VLOOKUP("Argentina"&$K10,Datos!$H:$I,2,0)),"Error")) -> 0.14 | P10: =IF($M10="","",IFERROR(-$M10*$O10,"Error")) -> -3598 | Q10: =IF($M10="","",IFERROR(-($P10-$P10/(1+Datos!$B$2)),"Error")) -> 624.44628 | R10: =IF($M10="","",IF($M10<=15000,-1000,IF($M10<=25000,-2000,IF($M10<=33000,-2400,0)))) -> -2400 | S10: =IF($M10="","",-($R10-$R10/(1+Datos!$B$2))) -> 416.52893 | T10: =IF($M10="","",-$M10/(1+$L10)*$L10) -> -4460.3306 | U10: =IF($M10="","",$C10*$D10) -> 2857.68 | V10: =IF($M10="","",-N($N10)) -> 0 | W10: =IF($M10="","",-($V10-$V10/(1+Datos!$B$2))) -> 0 | X10: =IF($M10="","",-$M10*Datos!$C$2) -> -1207.9 | Y10: =IF($M10="","",IFERROR($M10+$U10+$T10+$P10+$Q10+$R10+$S10+$V10+$W10+$X10,"Error")) -> 17932.425 | Z10: =IF($M10="","",IFERROR($Y10-$E10,"Error")) -> 1466.7446 | AA10: =IF($M10="","",IFERROR($Z10/($M10+$T10),"Error")) -> 0.069056848 | AB10: =IF($M10="","",IFERROR($M10/$E10,"Error")) -> 1.5608223 | AD10: 25700 | AE10: Repuesto Cuchilla Cortadora Oleo Mac Ge47 Ra · 30 u. (confirmar que sea la misma cuchilla) | AF10: 0.15 | AG10: =IF(N($AD10)=0,"",IFERROR(($AD10/(1+$L10)-($AD10*$O10+IF($AD10<=15000,1000,IF($AD10<=25000,2000,IF($AD10<=33000,2400,0)))+N($N10))/(1+Datos!$B$2)-$AD10*Datos!$C$2-$C10)/($AD10/(1+$L10)),"Error")) -> 0.069056848 | AH10: =IF(N($AD10)=0,"",IFERROR($AD10/(1+$L10)*(1-$AF10)-($AD10*$O10+IF($AD10<=15000,1000,IF($AD10<=25000,2000,IF($AD10<=33000,2400,0)))+N($N10))/(1+Datos!$B$2)-$AD10*Datos!$C$2,"Error")) -> 11888.794 | AI10: =IF($AH10="","",IFERROR($AH10*(1+$D10),"Error")) -> 14385.441 | AJ10: =IF($AH10="","",IFERROR($C10/$AH10-1,"Error")) -> 0.14460725 | AK10: =IF($AH10="","",IFERROR(IF($C10<=$AH10,"OK a ese precio","Bajar costo"),"Error")) -> Bajar costo
E11: =IF($C11="","",$C11*(1+$D11)) | O11: =IF($M11="","",IFERROR(IF($K11="Clásica",VLOOKUP("Argentina"&$J11,Datos!$C:$D,2,0),VLOOKUP("Argentina"&$J11,Datos!$C:$D,2,0)+VLOOKUP("Argentina"&$K11,Datos!$H:$I,2,0)),"Error")) | P11: =IF($M11="","",IFERROR(-$M11*$O11,"Error")) | Q11: =IF($M11="","",IFERROR(-($P11-$P11/(1+Datos!$B$2)),"Error")) | R11: =IF($M11="","",IF($M11<=15000,-1000,IF($M11<=25000,-2000,IF($M11<=33000,-2400,0)))) | S11: =IF($M11="","",-($R11-$R11/(1+Datos!$B$2))) | T11: =IF($M11="","",-$M11/(1+$L11)*$L11) | U11: =IF($M11="","",$C11*$D11) | V11: =IF($M11="","",-N($N11)) | W11: =IF($M11="","",-($V11-$V11/(1+Datos!$B$2))) | X11: =IF($M11="","",-$M11*Datos!$C$2) | Y11: =IF($M11="","",IFERROR($M11+$U11+$T11+$P11+$Q11+$R11+$S11+$V11+$W11+$X11,"Error")) | Z11: =IF($M11="","",IFERROR($Y11-$E11,"Error")) | AA11: =IF($M11="","",IFERROR($Z11/($M11+$T11),"Error")) | AB11: =IF($M11="","",IFERROR($M11/$E11,"Error")) | AG11: =IF(N($AD11)=0,"",IFERROR(($AD11/(1+$L11)-($AD11*$O11+IF($AD11<=15000,1000,IF($AD11<=25000,2000,IF($AD11<=33000,2400,0)))+N($N11))/(1+Datos!$B$2)-$AD11*Datos!$C$2-$C11)/($AD11/(1+$L11)),"Error")) | AH11: =IF(N($AD11)=0,"",IFERROR($AD11/(1+$L11)*(1-$AF11)-($AD11*$O11+IF($AD11<=15000,1000,IF($AD11<=25000,2000,IF($AD11<=33000,2400,0)))+N($N11))/(1+Datos!$B$2)-$AD11*Datos!$C$2,"Error")) | AI11: =IF($AH11="","",IFERROR($AH11*(1+$D11),"Error")) | AJ11: =IF($AH11="","",IFERROR($C11/$AH11-1,"Error")) | AK11: =IF($AH11="","",IFERROR(IF($C11<=$AH11,"OK a ese precio","Bajar costo"),"Error"))
E12: =IF($C12="","",$C12*(1+$D12)) | O12: =IF($M12="","",IFERROR(IF($K12="Clásica",VLOOKUP("Argentina"&$J12,Datos!$C:$D,2,0),VLOOKUP("Argentina"&$J12,Datos!$C:$D,2,0)+VLOOKUP("Argentina"&$K12,Datos!$H:$I,2,0)),"Error")) | P12: =IF($M12="","",IFERROR(-$M12*$O12,"Error")) | Q12: =IF($M12="","",IFERROR(-($P12-$P12/(1+Datos!$B$2)),"Error")) | R12: =IF($M12="","",IF($M12<=15000,-1000,IF($M12<=25000,-2000,IF($M12<=33000,-2400,0)))) | S12: =IF($M12="","",-($R12-$R12/(1+Datos!$B$2))) | T12: =IF($M12="","",-$M12/(1+$L12)*$L12) | U12: =IF($M12="","",$C12*$D12) | V12: =IF($M12="","",-N($N12)) | W12: =IF($M12="","",-($V12-$V12/(1+Datos!$B$2))) | X12: =IF($M12="","",-$M12*Datos!$C$2) | Y12: =IF($M12="","",IFERROR($M12+$U12+$T12+$P12+$Q12+$R12+$S12+$V12+$W12+$X12,"Error")) | Z12: =IF($M12="","",IFERROR($Y12-$E12,"Error")) | AA12: =IF($M12="","",IFERROR($Z12/($M12+$T12),"Error")) | AB12: =IF($M12="","",IFERROR($M12/$E12,"Error")) | AG12: =IF(N($AD12)=0,"",IFERROR(($AD12/(1+$L12)-($AD12*$O12+IF($AD12<=15000,1000,IF($AD12<=25000,2000,IF($AD12<=33000,2400,0)))+N($N12))/(1+Datos!$B$2)-$AD12*Datos!$C$2-$C12)/($AD12/(1+$L12)),"Error")) | AH12: =IF(N($AD12)=0,"",IFERROR($AD12/(1+$L12)*(1-$AF12)-($AD12*$O12+IF($AD12<=15000,1000,IF($AD12<=25000,2000,IF($AD12<=33000,2400,0)))+N($N12))/(1+Datos!$B$2)-$AD12*Datos!$C$2,"Error")) | AI12: =IF($AH12="","",IFERROR($AH12*(1+$D12),"Error")) | AJ12: =IF($AH12="","",IFERROR($C12/$AH12-1,"Error")) | AK12: =IF($AH12="","",IFERROR(IF($C12<=$AH12,"OK a ese precio","Bajar costo"),"Error"))
E13: =IF($C13="","",$C13*(1+$D13)) | O13: =IF($M13="","",IFERROR(IF($K13="Clásica",VLOOKUP("Argentina"&$J13,Datos!$C:$D,2,0),VLOOKUP("Argentina"&$J13,Datos!$C:$D,2,0)+VLOOKUP("Argentina"&$K13,Datos!$H:$I,2,0)),"Error")) | P13: =IF($M13="","",IFERROR(-$M13*$O13,"Error")) | Q13: =IF($M13="","",IFERROR(-($P13-$P13/(1+Datos!$B$2)),"Error")) | R13: =IF($M13="","",IF($M13<=15000,-1000,IF($M13<=25000,-2000,IF($M13<=33000,-2400,0)))) | S13: =IF($M13="","",-($R13-$R13/(1+Datos!$B$2))) | T13: =IF($M13="","",-$M13/(1+$L13)*$L13) | U13: =IF($M13="","",$C13*$D13) | V13: =IF($M13="","",-N($N13)) | W13: =IF($M13="","",-($V13-$V13/(1+Datos!$B$2))) | X13: =IF($M13="","",-$M13*Datos!$C$2) | Y13: =IF($M13="","",IFERROR($M13+$U13+$T13+$P13+$Q13+$R13+$S13+$V13+$W13+$X13,"Error")) | Z13: =IF($M13="","",IFERROR($Y13-$E13,"Error")) | AA13: =IF($M13="","",IFERROR($Z13/($M13+$T13),"Error")) | AB13: =IF($M13="","",IFERROR($M13/$E13,"Error")) | AG13: =IF(N($AD13)=0,"",IFERROR(($AD13/(1+$L13)-($AD13*$O13+IF($AD13<=15000,1000,IF($AD13<=25000,2000,IF($AD13<=33000,2400,0)))+N($N13))/(1+Datos!$B$2)-$AD13*Datos!$C$2-$C13)/($AD13/(1+$L13)),"Error")) | AH13: =IF(N($AD13)=0,"",IFERROR($AD13/(1+$L13)*(1-$AF13)-($AD13*$O13+IF($AD13<=15000,1000,IF($AD13<=25000,2000,IF($AD13<=33000,2400,0)))+N($N13))/(1+Datos!$B$2)-$AD13*Datos!$C$2,"Error")) | AI13: =IF($AH13="","",IFERROR($AH13*(1+$D13),"Error")) | AJ13: =IF($AH13="","",IFERROR($C13/$AH13-1,"Error")) | AK13: =IF($AH13="","",IFERROR(IF($C13<=$AH13,"OK a ese precio","Bajar costo"),"Error"))
E14: =IF($C14="","",$C14*(1+$D14)) | O14: =IF($M14="","",IFERROR(IF($K14="Clásica",VLOOKUP("Argentina"&$J14,Datos!$C:$D,2,0),VLOOKUP("Argentina"&$J14,Datos!$C:$D,2,0)+VLOOKUP("Argentina"&$K14,Datos!$H:$I,2,0)),"Error")) | P14: =IF($M14="","",IFERROR(-$M14*$O14,"Error")) | Q14: =IF($M14="","",IFERROR(-($P14-$P14/(1+Datos!$B$2)),"Error")) | R14: =IF($M14="","",IF($M14<=15000,-1000,IF($M14<=25000,-2000,IF($M14<=33000,-2400,0)))) | S14: =IF($M14="","",-($R14-$R14/(1+Datos!$B$2))) | T14: =IF($M14="","",-$M14/(1+$L14)*$L14) | U14: =IF($M14="","",$C14*$D14) | V14: =IF($M14="","",-N($N14)) | W14: =IF($M14="","",-($V14-$V14/(1+Datos!$B$2))) | X14: =IF($M14="","",-$M14*Datos!$C$2) | Y14: =IF($M14="","",IFERROR($M14+$U14+$T14+$P14+$Q14+$R14+$S14+$V14+$W14+$X14,"Error")) | Z14: =IF($M14="","",IFERROR($Y14-$E14,"Error")) | AA14: =IF($M14="","",IFERROR($Z14/($M14+$T14),"Error")) | AB14: =IF($M14="","",IFERROR($M14/$E14,"Error")) | AG14: =IF(N($AD14)=0,"",IFERROR(($AD14/(1+$L14)-($AD14*$O14+IF($AD14<=15000,1000,IF($AD14<=25000,2000,IF($AD14<=33000,2400,0)))+N($N14))/(1+Datos!$B$2)-$AD14*Datos!$C$2-$C14)/($AD14/(1+$L14)),"Error")) | AH14: =IF(N($AD14)=0,"",IFERROR($AD14/(1+$L14)*(1-$AF14)-($AD14*$O14+IF($AD14<=15000,1000,IF($AD14<=25000,2000,IF($AD14<=33000,2400,0)))+N($N14))/(1+Datos!$B$2)-$AD14*Datos!$C$2,"Error")) | AI14: =IF($AH14="","",IFERROR($AH14*(1+$D14),"Error")) | AJ14: =IF($AH14="","",IFERROR($C14/$AH14-1,"Error")) | AK14: =IF($AH14="","",IFERROR(IF($C14<=$AH14,"OK a ese precio","Bajar costo"),"Error"))
E15: =IF($C15="","",$C15*(1+$D15)) | O15: =IF($M15="","",IFERROR(IF($K15="Clásica",VLOOKUP("Argentina"&$J15,Datos!$C:$D,2,0),VLOOKUP("Argentina"&$J15,Datos!$C:$D,2,0)+VLOOKUP("Argentina"&$K15,Datos!$H:$I,2,0)),"Error")) | P15: =IF($M15="","",IFERROR(-$M15*$O15,"Error")) | Q15: =IF($M15="","",IFERROR(-($P15-$P15/(1+Datos!$B$2)),"Error")) | R15: =IF($M15="","",IF($M15<=15000,-1000,IF($M15<=25000,-2000,IF($M15<=33000,-2400,0)))) | S15: =IF($M15="","",-($R15-$R15/(1+Datos!$B$2))) | T15: =IF($M15="","",-$M15/(1+$L15)*$L15) | U15: =IF($M15="","",$C15*$D15) | V15: =IF($M15="","",-N($N15)) | W15: =IF($M15="","",-($V15-$V15/(1+Datos!$B$2))) | X15: =IF($M15="","",-$M15*Datos!$C$2) | Y15: =IF($M15="","",IFERROR($M15+$U15+$T15+$P15+$Q15+$R15+$S15+$V15+$W15+$X15,"Error")) | Z15: =IF($M15="","",IFERROR($Y15-$E15,"Error")) | AA15: =IF($M15="","",IFERROR($Z15/($M15+$T15),"Error")) | AB15: =IF($M15="","",IFERROR($M15/$E15,"Error")) | AG15: =IF(N($AD15)=0,"",IFERROR(($AD15/(1+$L15)-($AD15*$O15+IF($AD15<=15000,1000,IF($AD15<=25000,2000,IF($AD15<=33000,2400,0)))+N($N15))/(1+Datos!$B$2)-$AD15*Datos!$C$2-$C15)/($AD15/(1+$L15)),"Error")) | AH15: =IF(N($AD15)=0,"",IFERROR($AD15/(1+$L15)*(1-$AF15)-($AD15*$O15+IF($AD15<=15000,1000,IF($AD15<=25000,2000,IF($AD15<=33000,2400,0)))+N($N15))/(1+Datos!$B$2)-$AD15*Datos!$C$2,"Error")) | AI15: =IF($AH15="","",IFERROR($AH15*(1+$D15),"Error")) | AJ15: =IF($AH15="","",IFERROR($C15/$AH15-1,"Error")) | AK15: =IF($AH15="","",IFERROR(IF($C15<=$AH15,"OK a ese precio","Bajar costo"),"Error"))
E16: =IF($C16="","",$C16*(1+$D16)) | O16: =IF($M16="","",IFERROR(IF($K16="Clásica",VLOOKUP("Argentina"&$J16,Datos!$C:$D,2,0),VLOOKUP("Argentina"&$J16,Datos!$C:$D,2,0)+VLOOKUP("Argentina"&$K16,Datos!$H:$I,2,0)),"Error")) | P16: =IF($M16="","",IFERROR(-$M16*$O16,"Error")) | Q16: =IF($M16="","",IFERROR(-($P16-$P16/(1+Datos!$B$2)),"Error")) | R16: =IF($M16="","",IF($M16<=15000,-1000,IF($M16<=25000,-2000,IF($M16<=33000,-2400,0)))) | S16: =IF($M16="","",-($R16-$R16/(1+Datos!$B$2))) | T16: =IF($M16="","",-$M16/(1+$L16)*$L16) | U16: =IF($M16="","",$C16*$D16) | V16: =IF($M16="","",-N($N16)) | W16: =IF($M16="","",-($V16-$V16/(1+Datos!$B$2))) | X16: =IF($M16="","",-$M16*Datos!$C$2) | Y16: =IF($M16="","",IFERROR($M16+$U16+$T16+$P16+$Q16+$R16+$S16+$V16+$W16+$X16,"Error")) | Z16: =IF($M16="","",IFERROR($Y16-$E16,"Error")) | AA16: =IF($M16="","",IFERROR($Z16/($M16+$T16),"Error")) | AB16: =IF($M16="","",IFERROR($M16/$E16,"Error")) | AG16: =IF(N($AD16)=0,"",IFERROR(($AD16/(1+$L16)-($AD16*$O16+IF($AD16<=15000,1000,IF($AD16<=25000,2000,IF($AD16<=33000,2400,0)))+N($N16))/(1+Datos!$B$2)-$AD16*Datos!$C$2-$C16)/($AD16/(1+$L16)),"Error")) | AH16: =IF(N($AD16)=0,"",IFERROR($AD16/(1+$L16)*(1-$AF16)-($AD16*$O16+IF($AD16<=15000,1000,IF($AD16<=25000,2000,IF($AD16<=33000,2400,0)))+N($N16))/(1+Datos!$B$2)-$AD16*Datos!$C$2,"Error")) | AI16: =IF($AH16="","",IFERROR($AH16*(1+$D16),"Error")) | AJ16: =IF($AH16="","",IFERROR($C16/$AH16-1,"Error")) | AK16: =IF($AH16="","",IFERROR(IF($C16<=$AH16,"OK a ese precio","Bajar costo"),"Error"))
E17: =IF($C17="","",$C17*(1+$D17)) | O17: =IF($M17="","",IFERROR(IF($K17="Clásica",VLOOKUP("Argentina"&$J17,Datos!$C:$D,2,0),VLOOKUP("Argentina"&$J17,Datos!$C:$D,2,0)+VLOOKUP("Argentina"&$K17,Datos!$H:$I,2,0)),"Error")) | P17: =IF($M17="","",IFERROR(-$M17*$O17,"Error")) | Q17: =IF($M17="","",IFERROR(-($P17-$P17/(1+Datos!$B$2)),"Error")) | R17: =IF($M17="","",IF($M17<=15000,-1000,IF($M17<=25000,-2000,IF($M17<=33000,-2400,0)))) | S17: =IF($M17="","",-($R17-$R17/(1+Datos!$B$2))) | T17: =IF($M17="","",-$M17/(1+$L17)*$L17) | U17: =IF($M17="","",$C17*$D17) | V17: =IF($M17="","",-N($N17)) | W17: =IF($M17="","",-($V17-$V17/(1+Datos!$B$2))) | X17: =IF($M17="","",-$M17*Datos!$C$2) | Y17: =IF($M17="","",IFERROR($M17+$U17+$T17+$P17+$Q17+$R17+$S17+$V17+$W17+$X17,"Error")) | Z17: =IF($M17="","",IFERROR($Y17-$E17,"Error")) | AA17: =IF($M17="","",IFERROR($Z17/($M17+$T17),"Error")) | AB17: =IF($M17="","",IFERROR($M17/$E17,"Error")) | AG17: =IF(N($AD17)=0,"",IFERROR(($AD17/(1+$L17)-($AD17*$O17+IF($AD17<=15000,1000,IF($AD17<=25000,2000,IF($AD17<=33000,2400,0)))+N($N17))/(1+Datos!$B$2)-$AD17*Datos!$C$2-$C17)/($AD17/(1+$L17)),"Error")) | AH17: =IF(N($AD17)=0,"",IFERROR($AD17/(1+$L17)*(1-$AF17)-($AD17*$O17+IF($AD17<=15000,1000,IF($AD17<=25000,2000,IF($AD17<=33000,2400,0)))+N($N17))/(1+Datos!$B$2)-$AD17*Datos!$C$2,"Error")) | AI17: =IF($AH17="","",IFERROR($AH17*(1+$D17),"Error")) | AJ17: =IF($AH17="","",IFERROR($C17/$AH17-1,"Error")) | AK17: =IF($AH17="","",IFERROR(IF($C17<=$AH17,"OK a ese precio","Bajar costo"),"Error"))
E18: =IF($C18="","",$C18*(1+$D18)) | O18: =IF($M18="","",IFERROR(IF($K18="Clásica",VLOOKUP("Argentina"&$J18,Datos!$C:$D,2,0),VLOOKUP("Argentina"&$J18,Datos!$C:$D,2,0)+VLOOKUP("Argentina"&$K18,Datos!$H:$I,2,0)),"Error")) | P18: =IF($M18="","",IFERROR(-$M18*$O18,"Error")) | Q18: =IF($M18="","",IFERROR(-($P18-$P18/(1+Datos!$B$2)),"Error")) | R18: =IF($M18="","",IF($M18<=15000,-1000,IF($M18<=25000,-2000,IF($M18<=33000,-2400,0)))) | S18: =IF($M18="","",-($R18-$R18/(1+Datos!$B$2))) | T18: =IF($M18="","",-$M18/(1+$L18)*$L18) | U18: =IF($M18="","",$C18*$D18) | V18: =IF($M18="","",-N($N18)) | W18: =IF($M18="","",-($V18-$V18/(1+Datos!$B$2))) | X18: =IF($M18="","",-$M18*Datos!$C$2) | Y18: =IF($M18="","",IFERROR($M18+$U18+$T18+$P18+$Q18+$R18+$S18+$V18+$W18+$X18,"Error")) | Z18: =IF($M18="","",IFERROR($Y18-$E18,"Error")) | AA18: =IF($M18="","",IFERROR($Z18/($M18+$T18),"Error")) | AB18: =IF($M18="","",IFERROR($M18/$E18,"Error")) | AG18: =IF(N($AD18)=0,"",IFERROR(($AD18/(1+$L18)-($AD18*$O18+IF($AD18<=15000,1000,IF($AD18<=25000,2000,IF($AD18<=33000,2400,0)))+N($N18))/(1+Datos!$B$2)-$AD18*Datos!$C$2-$C18)/($AD18/(1+$L18)),"Error")) | AH18: =IF(N($AD18)=0,"",IFERROR($AD18/(1+$L18)*(1-$AF18)-($AD18*$O18+IF($AD18<=15000,1000,IF($AD18<=25000,2000,IF($AD18<=33000,2400,0)))+N($N18))/(1+Datos!$B$2)-$AD18*Datos!$C$2,"Error")) | AI18: =IF($AH18="","",IFERROR($AH18*(1+$D18),"Error")) | AJ18: =IF($AH18="","",IFERROR($C18/$AH18-1,"Error")) | AK18: =IF($AH18="","",IFERROR(IF($C18<=$AH18,"OK a ese precio","Bajar costo"),"Error"))
E19: =IF($C19="","",$C19*(1+$D19)) | O19: =IF($M19="","",IFERROR(IF($K19="Clásica",VLOOKUP("Argentina"&$J19,Datos!$C:$D,2,0),VLOOKUP("Argentina"&$J19,Datos!$C:$D,2,0)+VLOOKUP("Argentina"&$K19,Datos!$H:$I,2,0)),"Error")) | P19: =IF($M19="","",IFERROR(-$M19*$O19,"Error")) | Q19: =IF($M19="","",IFERROR(-($P19-$P19/(1+Datos!$B$2)),"Error")) | R19: =IF($M19="","",IF($M19<=15000,-1000,IF($M19<=25000,-2000,IF($M19<=33000,-2400,0)))) | S19: =IF($M19="","",-($R19-$R19/(1+Datos!$B$2))) | T19: =IF($M19="","",-$M19/(1+$L19)*$L19) | U19: =IF($M19="","",$C19*$D19) | V19: =IF($M19="","",-N($N19)) | W19: =IF($M19="","",-($V19-$V19/(1+Datos!$B$2))) | X19: =IF($M19="","",-$M19*Datos!$C$2) | Y19: =IF($M19="","",IFERROR($M19+$U19+$T19+$P19+$Q19+$R19+$S19+$V19+$W19+$X19,"Error")) | Z19: =IF($M19="","",IFERROR($Y19-$E19,"Error")) | AA19: =IF($M19="","",IFERROR($Z19/($M19+$T19),"Error")) | AB19: =IF($M19="","",IFERROR($M19/$E19,"Error")) | AG19: =IF(N($AD19)=0,"",IFERROR(($AD19/(1+$L19)-($AD19*$O19+IF($AD19<=15000,1000,IF($AD19<=25000,2000,IF($AD19<=33000,2400,0)))+N($N19))/(1+Datos!$B$2)-$AD19*Datos!$C$2-$C19)/($AD19/(1+$L19)),"Error")) | AH19: =IF(N($AD19)=0,"",IFERROR($AD19/(1+$L19)*(1-$AF19)-($AD19*$O19+IF($AD19<=15000,1000,IF($AD19<=25000,2000,IF($AD19<=33000,2400,0)))+N($N19))/(1+Datos!$B$2)-$AD19*Datos!$C$2,"Error")) | AI19: =IF($AH19="","",IFERROR($AH19*(1+$D19),"Error")) | AJ19: =IF($AH19="","",IFERROR($C19/$AH19-1,"Error")) | AK19: =IF($AH19="","",IFERROR(IF($C19<=$AH19,"OK a ese precio","Bajar costo"),"Error"))
E20: =IF($C20="","",$C20*(1+$D20)) | O20: =IF($M20="","",IFERROR(IF($K20="Clásica",VLOOKUP("Argentina"&$J20,Datos!$C:$D,2,0),VLOOKUP("Argentina"&$J20,Datos!$C:$D,2,0)+VLOOKUP("Argentina"&$K20,Datos!$H:$I,2,0)),"Error")) | P20: =IF($M20="","",IFERROR(-$M20*$O20,"Error")) | Q20: =IF($M20="","",IFERROR(-($P20-$P20/(1+Datos!$B$2)),"Error")) | R20: =IF($M20="","",IF($M20<=15000,-1000,IF($M20<=25000,-2000,IF($M20<=33000,-2400,0)))) | S20: =IF($M20="","",-($R20-$R20/(1+Datos!$B$2))) | T20: =IF($M20="","",-$M20/(1+$L20)*$L20) | U20: =IF($M20="","",$C20*$D20) | V20: =IF($M20="","",-N($N20)) | W20: =IF($M20="","",-($V20-$V20/(1+Datos!$B$2))) | X20: =IF($M20="","",-$M20*Datos!$C$2) | Y20: =IF($M20="","",IFERROR($M20+$U20+$T20+$P20+$Q20+$R20+$S20+$V20+$W20+$X20,"Error")) | Z20: =IF($M20="","",IFERROR($Y20-$E20,"Error")) | AA20: =IF($M20="","",IFERROR($Z20/($M20+$T20),"Error")) | AB20: =IF($M20="","",IFERROR($M20/$E20,"Error")) | AG20: =IF(N($AD20)=0,"",IFERROR(($AD20/(1+$L20)-($AD20*$O20+IF($AD20<=15000,1000,IF($AD20<=25000,2000,IF($AD20<=33000,2400,0)))+N($N20))/(1+Datos!$B$2)-$AD20*Datos!$C$2-$C20)/($AD20/(1+$L20)),"Error")) | AH20: =IF(N($AD20)=0,"",IFERROR($AD20/(1+$L20)*(1-$AF20)-($AD20*$O20+IF($AD20<=15000,1000,IF($AD20<=25000,2000,IF($AD20<=33000,2400,0)))+N($N20))/(1+Datos!$B$2)-$AD20*Datos!$C$2,"Error")) | AI20: =IF($AH20="","",IFERROR($AH20*(1+$D20),"Error")) | AJ20: =IF($AH20="","",IFERROR($C20/$AH20-1,"Error")) | AK20: =IF($AH20="","",IFERROR(IF($C20<=$AH20,"OK a ese precio","Bajar costo"),"Error"))
E21: =IF($C21="","",$C21*(1+$D21)) | O21: =IF($M21="","",IFERROR(IF($K21="Clásica",VLOOKUP("Argentina"&$J21,Datos!$C:$D,2,0),VLOOKUP("Argentina"&$J21,Datos!$C:$D,2,0)+VLOOKUP("Argentina"&$K21,Datos!$H:$I,2,0)),"Error")) | P21: =IF($M21="","",IFERROR(-$M21*$O21,"Error")) | Q21: =IF($M21="","",IFERROR(-($P21-$P21/(1+Datos!$B$2)),"Error")) | R21: =IF($M21="","",IF($M21<=15000,-1000,IF($M21<=25000,-2000,IF($M21<=33000,-2400,0)))) | S21: =IF($M21="","",-($R21-$R21/(1+Datos!$B$2))) | T21: =IF($M21="","",-$M21/(1+$L21)*$L21) | U21: =IF($M21="","",$C21*$D21) | V21: =IF($M21="","",-N($N21)) | W21: =IF($M21="","",-($V21-$V21/(1+Datos!$B$2))) | X21: =IF($M21="","",-$M21*Datos!$C$2) | Y21: =IF($M21="","",IFERROR($M21+$U21+$T21+$P21+$Q21+$R21+$S21+$V21+$W21+$X21,"Error")) | Z21: =IF($M21="","",IFERROR($Y21-$E21,"Error")) | AA21: =IF($M21="","",IFERROR($Z21/($M21+$T21),"Error")) | AB21: =IF($M21="","",IFERROR($M21/$E21,"Error")) | AG21: =IF(N($AD21)=0,"",IFERROR(($AD21/(1+$L21)-($AD21*$O21+IF($AD21<=15000,1000,IF($AD21<=25000,2000,IF($AD21<=33000,2400,0)))+N($N21))/(1+Datos!$B$2)-$AD21*Datos!$C$2-$C21)/($AD21/(1+$L21)),"Error")) | AH21: =IF(N($AD21)=0,"",IFERROR($AD21/(1+$L21)*(1-$AF21)-($AD21*$O21+IF($AD21<=15000,1000,IF($AD21<=25000,2000,IF($AD21<=33000,2400,0)))+N($N21))/(1+Datos!$B$2)-$AD21*Datos!$C$2,"Error")) | AI21: =IF($AH21="","",IFERROR($AH21*(1+$D21),"Error")) | AJ21: =IF($AH21="","",IFERROR($C21/$AH21-1,"Error")) | AK21: =IF($AH21="","",IFERROR(IF($C21<=$AH21,"OK a ese precio","Bajar costo"),"Error"))
E22: =IF($C22="","",$C22*(1+$D22)) | O22: =IF($M22="","",IFERROR(IF($K22="Clásica",VLOOKUP("Argentina"&$J22,Datos!$C:$D,2,0),VLOOKUP("Argentina"&$J22,Datos!$C:$D,2,0)+VLOOKUP("Argentina"&$K22,Datos!$H:$I,2,0)),"Error")) | P22: =IF($M22="","",IFERROR(-$M22*$O22,"Error")) | Q22: =IF($M22="","",IFERROR(-($P22-$P22/(1+Datos!$B$2)),"Error")) | R22: =IF($M22="","",IF($M22<=15000,-1000,IF($M22<=25000,-2000,IF($M22<=33000,-2400,0)))) | S22: =IF($M22="","",-($R22-$R22/(1+Datos!$B$2))) | T22: =IF($M22="","",-$M22/(1+$L22)*$L22) | U22: =IF($M22="","",$C22*$D22) | V22: =IF($M22="","",-N($N22)) | W22: =IF($M22="","",-($V22-$V22/(1+Datos!$B$2))) | X22: =IF($M22="","",-$M22*Datos!$C$2) | Y22: =IF($M22="","",IFERROR($M22+$U22+$T22+$P22+$Q22+$R22+$S22+$V22+$W22+$X22,"Error")) | Z22: =IF($M22="","",IFERROR($Y22-$E22,"Error")) | AA22: =IF($M22="","",IFERROR($Z22/($M22+$T22),"Error")) | AB22: =IF($M22="","",IFERROR($M22/$E22,"Error")) | AG22: =IF(N($AD22)=0,"",IFERROR(($AD22/(1+$L22)-($AD22*$O22+IF($AD22<=15000,1000,IF($AD22<=25000,2000,IF($AD22<=33000,2400,0)))+N($N22))/(1+Datos!$B$2)-$AD22*Datos!$C$2-$C22)/($AD22/(1+$L22)),"Error")) | AH22: =IF(N($AD22)=0,"",IFERROR($AD22/(1+$L22)*(1-$AF22)-($AD22*$O22+IF($AD22<=15000,1000,IF($AD22<=25000,2000,IF($AD22<=33000,2400,0)))+N($N22))/(1+Datos!$B$2)-$AD22*Datos!$C$2,"Error")) | AI22: =IF($AH22="","",IFERROR($AH22*(1+$D22),"Error")) | AJ22: =IF($AH22="","",IFERROR($C22/$AH22-1,"Error")) | AK22: =IF($AH22="","",IFERROR(IF($C22<=$AH22,"OK a ese precio","Bajar costo"),"Error"))
... E300: =IF($C300="","",$C300*(1+$D300)) | O300: =IF($M300="","",IFERROR(IF($K300="Clásica",VLOOKUP("Argentina"&$J300,Datos!$C:$D,2,0),VLOOKUP("Argentina"&$J300,Datos!$C:$D,2,0)+VLOOKUP("Argentina"&$K300,Datos!$H:$I,2,0)),"Error")) | P300: =IF($M300="","",IFERROR(-$M300*$O300,"Error")) | Q300: =IF($M300="","",IFERROR(-($P300-$P300/(1+Datos!$B$2)),"Error")) | R300: =IF($M300="","",IF($M300<=15000,-1000,IF($M300<=25000,-2000,IF($M300<=33000,-2400,0)))) | S300: =IF($M300="","",-($R300-$R300/(1+Datos!$B$2))) | T300: =IF($M300="","",-$M300/(1+$L300)*$L300) | U300: =IF($M300="","",$C300*$D300) | V300: =IF($M300="","",-N($N300)) | W300: =IF($M300="","",-($V300-$V300/(1+Datos!$B$2))) | X300: =IF($M300="","",-$M300*Datos!$C$2) | Y300: =IF($M300="","",IFERROR($M300+$U300+$T300+$P300+$Q300+$R300+$S300+$V300+$W300+$X300,"Error")) | Z300: =IF($M300="","",IFERROR($Y300-$E300,"Error")) | AA300: =IF($M300="","",IFERROR($Z300/($M300+$T300),"Error")) | AB300: =IF($M300="","",IFERROR($M300/$E300,"Error")) | AG300: =IF(N($AD300)=0,"",IFERROR(($AD300/(1+$L300)-($AD300*$O300+IF($AD300<=15000,1000,IF($AD300<=25000,2000,IF($AD300<=33000,2400,0)))+N($N300))/(1+Datos!$B$2)-$AD300*Datos!$C$2-$C300)/($AD300/(1+$L300)),"Error")) | AH300: =IF(N($AD300)=0,"",IFERROR($AD300/(1+$L300)*(1-$AF300)-($AD300*$O300+IF($AD300<=15000,1000,IF($AD300<=25000,2000,IF($AD300<=33000,2400,0)))+N($N300))/(1+Datos!$B$2)-$AD300*Datos!$C$2,"Error")) | AI300: =IF($AH300="","",IFERROR($AH300*(1+$D300),"Error")) | AJ300: =IF($AH300="","",IFERROR($C300/$AH300-1,"Error")) | AK300: =IF($AH300="","",IFERROR(IF($C300<=$AH300,"OK a ese precio","Bajar costo"),"Error"))
